setup.py
param_info/Bundle.py
param_info/Errors.py
param_info/Param.py
param_info/ParamBool.py
param_info/ParamInt.py
param_info/ParamStr.py
param_info/ParamVal.py
param_info/__init__.py
param_info/helpers.py
param_info.egg-info/PKG-INFO
param_info.egg-info/SOURCES.txt
param_info.egg-info/dependency_links.txt
param_info.egg-info/top_level.txt