Metadata-Version: 1.1
Name: param-info
Version: 0.2.0
Summary: A python package for parsing parameters.
Home-page: https://github.com/napuzba/param-info.git
Author: napuzba
Author-email: kobi@napuzba.com
License: MIT
Download-URL: https://github.com/napuzba/param-info/releases
Keywords: validate
Platform: UNKNOWN
Classifier: Topic :: Software Development :: Libraries :: Python Modules
Classifier: Programming Language :: Python :: 3
Classifier: Operating System :: OS Independent
Classifier: License :: OSI Approved :: MIT License
Classifier: Development Status :: 3 - Alpha
